lka_nic_decoder.py
lka_nic_decoder-1.0.18.dist-info/licenses/LICENSE
lka_nic_decoder-1.0.18.dist-info/METADATA
lka_nic_decoder-1.0.18.dist-info/WHEEL
lka_nic_decoder-1.0.18.dist-info/entry_points.txt
lka_nic_decoder-1.0.18.dist-info/top_level.txt
lka_nic_decoder-1.0.18.dist-info/RECORD
