Metadata-Version: 2.4
Name: lka-nic-decoder
Version: 1.0.18
Summary: Decode Sri Lankan NIC numbers into birth date, gender, and NIC type
Home-page: https://github.com/dilith-lab/srilanka-nic-decoder
Author: Dilith Achalan
Author-email: Dilith Achalan <dilith.achalan@outlook.com>
License: MIT
Project-URL: Homepage, https://github.com/dilith-lab/srilanka-nic-decoder
Project-URL: Repository, https://github.com/dilith-lab/srilanka-nic-decoder
Keywords: Sri Lanka,NIC,National Identity Card,NIC Decoder,Birth Date,Gender
Classifier: Programming Language :: Python :: 3
Classifier: License :: OSI Approved :: MIT License
Classifier: Operating System :: OS Independent
Classifier: Development Status :: 4 - Beta
Classifier: Intended Audience :: Developers
Classifier: Topic :: Software Development :: Libraries :: Python Modules
Requires-Python: >=3.8
License-File: LICENSE
Dynamic: license-file
